README.md
setup.py
two_eyes.egg-info/PKG-INFO
two_eyes.egg-info/SOURCES.txt
two_eyes.egg-info/dependency_links.txt
two_eyes.egg-info/not-zip-safe
two_eyes.egg-info/requires.txt
two_eyes.egg-info/top_level.txt
twoeyes/__init__.py
twoeyes/imports.py
twoeyes/interface.py
twoeyes/iplot.py
twoeyes/stereo.py
twoeyes/version.py