Metadata-Version: 1.2
Name: two-eyes
Version: 0.0.12
Summary: Stereogram images for ASTR1030.
Home-page: https://github.com/zkbt/two-eyes
Author: Zach Berta-Thompson
Author-email: zach.bertathompson@colorado.edu
License: MIT
Platform: UNKNOWN
Classifier: Intended Audience :: Education
Classifier: Intended Audience :: Science/Research
Classifier: Programming Language :: Python
Classifier: Topic :: Scientific/Engineering :: Astronomy
Requires-Python: >=3.6
